swahili_stopwords/__init__.py
swahili_stopwords/stopwords.py
swahili_stopwords-0.1.0.dist-info/LICENSE
swahili_stopwords-0.1.0.dist-info/METADATA
swahili_stopwords-0.1.0.dist-info/WHEEL
swahili_stopwords-0.1.0.dist-info/top_level.txt
swahili_stopwords-0.1.0.dist-info/RECORD
