Metadata-Version: 2.1
Name: swahili_stopwords
Version: 0.1.0
Summary: A library for Swahili stopwords
Home-page: https://github.com/alfredkondoro/swahili_stopwords
Author: Alfred Malengo Kondoro
Author-email: alfredkondoro97@gmail.com
License: MIT
Platform: UNKNOWN
Classifier: Programming Language :: Python :: 3
Classifier: License :: OSI Approved :: MIT License
Classifier: Operating System :: OS Independent
Requires-Python: >=3.6
License-File: LICENSE
